agentbench/__init__.py
agentbench/core/__init__.py
agentbench/core/agent.py
agentbench/core/composite_judge.py
agentbench/core/cost.py
agentbench/core/judge.py
agentbench/core/metadata.py
agentbench/core/result.py
agentbench/core/scenario.py
agentbench/core/task.py
agentbench/core/trace.py
agentbench/engine/__init__.py
agentbench/engine/runner.py
agentbench/engine/storage.py
agentbench/presets/__init__.py
agentbench/presets/judges.py
agentbench/presets/math_basic.py
agentbench/reporting/__init__.py
agentbench/reporting/compare.py
agentbench/reporting/html_report.py
agentbench/reporting/summary.py
agentbench/templates/report.html.j2
agentflowtest-0.0.1.dist-info/METADATA
agentflowtest-0.0.1.dist-info/WHEEL
agentflowtest-0.0.1.dist-info/licenses/LICENSE
agentflowtest-0.0.1.dist-info/RECORD
