Metadata-Version: 2.4
Name: agentflowtest
Version: 0.0.1
Summary: A simple evaluation harness for AI agents.
Project-URL: Homepage, https://github.com/geddydukes/agentbench
Project-URL: Documentation, https://github.com/geddydukes/agentbench#readme
Project-URL: Repository, https://github.com/geddydukes/agentbench
Project-URL: Issues, https://github.com/geddydukes/agentbench/issues
Author: Geddy Dukes
License: MIT
License-File: LICENSE
Keywords: agents,ai,benchmark,evaluation,llm,testing
Classifier: Development Status :: 3 - Alpha
Classifier: Intended Audience :: Developers
Classifier: License :: OSI Approved :: MIT License
Classifier: Programming Language :: Python :: 3
Classifier: Programming Language :: Python :: 3.11
Classifier: Programming Language :: Python :: 3.12
Classifier: Topic :: Scientific/Engineering :: Artificial Intelligence
Classifier: Topic :: Software Development :: Testing
Requires-Python: >=3.11
Requires-Dist: jinja2>=3.0.0
Provides-Extra: dev
Requires-Dist: pytest-asyncio>=0.21.0; extra == 'dev'
Requires-Dist: pytest-cov>=4.0.0; extra == 'dev'
Requires-Dist: pytest-html>=3.2.0; extra == 'dev'
Requires-Dist: pytest>=7.0.0; extra == 'dev'
